afplay/__init__.py
afplay/arguments.py
afplay/main.py
afplay/py.typed
afplay/types.py
afplay/util.py
afplay/validate.py
afplay/version.py
afplay_py-0.2.1.dist-info/LICENSE
afplay_py-0.2.1.dist-info/METADATA
afplay_py-0.2.1.dist-info/WHEEL
afplay_py-0.2.1.dist-info/entry_points.txt
afplay_py-0.2.1.dist-info/top_level.txt
afplay_py-0.2.1.dist-info/RECORD
